setup.py
src/impaf_haml.egg-info/PKG-INFO
src/impaf_haml.egg-info/SOURCES.txt
src/impaf_haml.egg-info/dependency_links.txt
src/impaf_haml.egg-info/namespace_packages.txt
src/impaf_haml.egg-info/not-zip-safe
src/impaf_haml.egg-info/requires.txt
src/impaf_haml.egg-info/top_level.txt
src/implugin/__init__.py
src/implugin/haml.py
src/implugin/test_haml.py