Metadata-Version: 1.0
Name: impaf-haml
Version: 0.1
Summary: Haml plugin for Impaf.
Home-page: UNKNOWN
Author: UNKNOWN
Author-email: UNKNOWN
License: Apache License 2.0
Platform: UNKNOWN
